playground/__init__.py
playground/main.py
cgrant_playground-0.1.3.dist-info/METADATA
cgrant_playground-0.1.3.dist-info/WHEEL
cgrant_playground-0.1.3.dist-info/top_level.txt
cgrant_playground-0.1.3.dist-info/RECORD
