Metadata-Version: 2.1
Name: cgrant_playground
Version: 0.1.3
Summary: Nothing to see here.
Home-page: https://github.com/christophergrant/playground
Author: Christopher Grant
Author-email: backfill@protonmail.com
License: MIT
Classifier: License :: OSI Approved :: MIT License
Classifier: Programming Language :: Python :: 3
Classifier: Programming Language :: Python :: 3 :: Only
Classifier: Programming Language :: Python :: Implementation :: CPython
Classifier: Programming Language :: Python :: Implementation :: PyPy
Requires-Python: >=3.7
